Metadata-Version: 2.1
Name: aiohttp-socksx
Version: 0.8.4
Summary: Proxy connector for aiohttp
Home-page: https://github.com/romis2012/aiohttp-socks
Author: Roman Snegirev
Author-email: snegiryev@gmail.com
License: Apache 2
Keywords: asyncio aiohttp socks socks5 socks4 http proxy
License-File: LICENSE.txt
Requires-Dist: aiohttp>=2.3.2
Requires-Dist: python-socks[asyncio]<3.0.0,>=2.4.3
